tagcash/__init__.py
tagcash/entry.py
tagcash/interface.py
tagcash-1.0.0b2.dist-info/DESCRIPTION.rst
tagcash-1.0.0b2.dist-info/METADATA
tagcash-1.0.0b2.dist-info/RECORD
tagcash-1.0.0b2.dist-info/WHEEL
tagcash-1.0.0b2.dist-info/entry_points.txt
tagcash-1.0.0b2.dist-info/metadata.json
tagcash-1.0.0b2.dist-info/top_level.txt
