Metadata-Version: 2.0
Name: tagcash
Version: 1.0.0b2
Summary: Finances with tags in CLI
Home-page: https://github.com/cemsbr/tagcash
Author: Carlos Eduardo Moreira dos Santos
Author-email: cems@cemshost.com.br
License: MIT
Keywords: accounting finance finances cli terminal
Platform: UNKNOWN
Classifier: Development Status :: 4 - Beta
Classifier: Intended Audience :: Developers
Classifier: Intended Audience :: Financial and Insurance Industry
Classifier: Topic :: Office/Business :: Financial :: Accounting
Classifier: License :: OSI Approved :: MIT License
Classifier: Programming Language :: Python :: 3.5
Classifier: Programming Language :: Python :: 3.6
Requires-Dist: docopt
Requires-Dist: terminaltables
Provides-Extra: dev
Requires-Dist: coverage (<4.4); extra == 'dev'
Requires-Dist: eradicate; extra == 'dev'
Requires-Dist: pip-tools; extra == 'dev'
Requires-Dist: rstcheck; extra == 'dev'
Requires-Dist: tox; extra == 'dev'
Requires-Dist: yala (>=1.4.0); extra == 'dev'
